setup.py
sslack.py
libslack/__init__.py
libslack/core/__init__.py
libslack/core/config.py
libslack/core/entry_point.py
libslack/core/plugin_management.py
libslack/default_plugins/__init__.py
sslack.egg-info/PKG-INFO
sslack.egg-info/SOURCES.txt
sslack.egg-info/dependency_links.txt
sslack.egg-info/entry_points.txt
sslack.egg-info/not-zip-safe
sslack.egg-info/requires.txt
sslack.egg-info/top_level.txt