Metadata-Version: 1.0
Name: sslack
Version: 0.1.1
Summary: Plugable platform for slack bots deevlopment.
Home-page: UNKNOWN
Author: magniff
Author-email: tinysnippest@gmail.com
License: MIT license
Platform: unix
Platform: linux
Platform: osx
Platform: cygwin
Platform: win32
